pyauthserver/__init__.py
pyauthserver/app.py
pyauthserver/config.py
pyauthserver/db.py
pyauthserver/model.py
pyauthserver/resplib.py
pyauthserver/session.py
pyauthserver/models/__init__.py
pyauthserver/models/user.py
pyauthserver/services/__init__.py
pyauthserver/services/admin.py
pyauthserver/services/login.py
pyauthserver/utils/__init__.py
pyauthserver/utils/db.py
pyauthserver/utils/fake_session.py
pyauthserver/utils/login.py
pyauthserver/utils/sign.py
pyauthserver/utils/simple.py
pyauthserver-0.0.0.3.dist-info/LICENSE
pyauthserver-0.0.0.3.dist-info/METADATA
pyauthserver-0.0.0.3.dist-info/WHEEL
pyauthserver-0.0.0.3.dist-info/entry_points.txt
pyauthserver-0.0.0.3.dist-info/top_level.txt
pyauthserver-0.0.0.3.dist-info/RECORD
